localstack_snapshot/__init__.py
localstack_snapshot/pytest/__init__.py
localstack_snapshot/pytest/snapshot.py
localstack_snapshot/snapshots/__init__.py
localstack_snapshot/snapshots/prototype.py
localstack_snapshot/snapshots/report.py
localstack_snapshot/snapshots/transformer.py
localstack_snapshot/snapshots/transformer_utility.py
localstack_snapshot/util/__init__.py
localstack_snapshot/util/encoding.py
localstack_snapshot-0.3.3.dist-info/licenses/LICENSE
localstack_snapshot-0.3.3.dist-info/METADATA
localstack_snapshot-0.3.3.dist-info/WHEEL
localstack_snapshot-0.3.3.dist-info/top_level.txt
localstack_snapshot-0.3.3.dist-info/RECORD
