Metadata-Version: 2.4
Name: localstack-snapshot
Version: 0.3.3
Summary: Extracted snapshot testing lib for LocalStack
Author-email: LocalStack Contributors <info@localstack.cloud>
License: 
Classifier: License :: OSI Approved :: Apache Software License
Classifier: Operating System :: OS Independent
Classifier: Programming Language :: Python :: 3
Classifier: Programming Language :: Python :: 3.10
Classifier: Programming Language :: Python :: 3.11
Classifier: Programming Language :: Python :: 3.12
Requires-Python: >=3.10
License-File: LICENSE
Requires-Dist: jsonpath-ng>1.6
Requires-Dist: deepdiff
Provides-Extra: dev
Requires-Dist: black==23.10.0; extra == "dev"
Requires-Dist: pytest>=7.0; extra == "dev"
Requires-Dist: coverage[toml]>=5.0.0; extra == "dev"
Requires-Dist: ruff==0.1.0; extra == "dev"
Dynamic: license-file
